LICENSE.txt
pypirc/__init__.py
pypirc/cmd.py
pypirc/pypirc.py
README.md
pypirc_voidei-1.1.0.dist-info/entry_points.txt
pypirc_voidei-1.1.0.dist-info/LICENSE.txt
pypirc_voidei-1.1.0.dist-info/METADATA
pypirc_voidei-1.1.0.dist-info/WHEEL
pypirc_voidei-1.1.0.dist-info/RECORD
