Metadata-Version: 2.1
Name: pypirc-voidei
Version: 1.1.0
Summary: PyPiRC: .pypirc Manager
Home-page: https://github.com/voidei/pypirc
License: Apache-2.0
Author: Greg Albrecht
Author-email: gba@splunk.com
Maintainer: Dawn Walker
Maintainer-email: dawniepieuwu@gmail.com
Requires-Python: >=3.11,<4
Classifier: License :: OSI Approved :: Apache Software License
Classifier: Programming Language :: Python :: 3
Classifier: Programming Language :: Python :: 3.11
Requires-Dist: prettyprinter (>=0.18.0,<0.19.0)
Project-URL: Repository, https://github.com/voidei/pypirc
Project-URL: pypirc-chappers, https://github.com/chappers/pypirc
Project-URL: pypirc-original, https://github.com/ampledata/pypirc
